hectofinancial_mcp_server/__init__.py
hectofinancial_mcp_server/server.py
hectofinancial_mcp_server/core/__init__.py
hectofinancial_mcp_server/core/document_repository.py
hectofinancial_mcp_server/core/search_engine.py
hectofinancial_mcp_server/core/utils/bm25_utils.py
hectofinancial_mcp_server/core/utils/category_map.json
hectofinancial_mcp_server/core/utils/category_utils.py
hectofinancial_mcp_server/core/utils/dynamic_keyword_processor.py
hectofinancial_mcp_server/core/utils/markdown_utils.py
hectofinancial_mcp_server/resource/.DS_Store
hectofinancial_mcp_server/resource/__init__.py
hectofinancial_mcp_server/resource/docs/.DS_Store
hectofinancial_mcp_server/resource/docs/__init__.py
hectofinancial_mcp_server/resource/docs/instructions.md
hectofinancial_mcp_server/resource/docs/encrypt/encryption_guide.md
hectofinancial_mcp_server/resource/docs/ezauth/hecto_financial_ezauth.md
hectofinancial_mcp_server/resource/docs/ezauth/settlePay.js
hectofinancial_mcp_server/resource/docs/ezcp/hecto_financial_ezcp.md
hectofinancial_mcp_server/resource/docs/pg/.DS_Store
hectofinancial_mcp_server/resource/docs/pg/hecto_financial_pg.md
hectofinancial_mcp_server/resource/docs/pg/hecto_financial_pg_banktransfer.md
hectofinancial_mcp_server/resource/docs/pg/hecto_financial_pg_creditcard.md
hectofinancial_mcp_server/resource/docs/pg/hecto_financial_pg_easypay.md
hectofinancial_mcp_server/resource/docs/pg/hecto_financial_pg_management.md
hectofinancial_mcp_server/resource/docs/pg/hecto_financial_pg_mobile.md
hectofinancial_mcp_server/resource/docs/pg/hecto_financial_pg_overview.md
hectofinancial_mcp_server/resource/docs/pg/hecto_financial_pg_virtualaccount.md
hectofinancial_mcp_server/resource/docs/pg/settlePG.js
hectofinancial_mcp_server/resource/docs/whitelabel/hecto_financial_whitelabel.md
hectofinancial_mcp_server/tools/__init__.py
hectofinancial_mcp_server/tools/get_docs.py
hectofinancial_mcp_server/tools/list_docs.py
hectofinancial_mcp_server/tools/search_docs.py
hectofinancial_mcp_server-0.1.16.dist-info/licenses/LICENSE
hectofinancial_mcp_server-0.1.16.dist-info/METADATA
hectofinancial_mcp_server-0.1.16.dist-info/WHEEL
hectofinancial_mcp_server-0.1.16.dist-info/entry_points.txt
hectofinancial_mcp_server-0.1.16.dist-info/top_level.txt
hectofinancial_mcp_server-0.1.16.dist-info/RECORD
