Metadata-Version: 2.4
Name: hectofinancial-mcp-server
Version: 0.1.16
Summary: 헥토파이낸셜 결제 서비스 연동 문서를 검색하고 조회할 수 있는 MCP 서버입니다. 공식 가이드를 AI와 함께 빠르게 탐색하여 정확한 결제 시스템 구축을 지원합니다.
Author-email: hectofinancial <pg_dev@hecto.co.kr>
License: MIT
Requires-Python: <4.0,>=3.10
License-File: LICENSE
Requires-Dist: mcp>=1.0.0
Requires-Dist: fastmcp>=0.1.0
Requires-Dist: mistune>=3.0.0
Requires-Dist: ruff>=0.12.0
Dynamic: license-file
